appcan_helper_mcp/__init__.py
appcan_helper_mcp/server.py
appcan_helper_mcp/utility.py
appcan_helper_mcp-1.0.1.dist-info/licenses/LICENSE
appcan_helper_mcp-1.0.1.dist-info/METADATA
appcan_helper_mcp-1.0.1.dist-info/WHEEL
appcan_helper_mcp-1.0.1.dist-info/entry_points.txt
appcan_helper_mcp-1.0.1.dist-info/top_level.txt
appcan_helper_mcp-1.0.1.dist-info/RECORD
