Metadata-Version: 2.4
Name: appcan-helper-mcp
Version: 1.0.1
Summary: AppCan Helper MCP Server - 提供 AppCan 开发规则以及官方文档查询功能
Author-email: zhangyipeng <sandy1108@163.com>
License: MIT
Project-URL: Homepage, https://github.com/yourusername/appcan-helper-mcp
Project-URL: Repository, https://github.com/yourusername/appcan-helper-mcp
Project-URL: Issues, https://github.com/yourusername/appcan-helper-mcp/issues
Keywords: mcp,appcan,documentation,ai,assistant
Classifier: Development Status :: 4 - Beta
Classifier: Intended Audience :: Developers
Classifier: License :: OSI Approved :: MIT License
Classifier: Programming Language :: Python :: 3
Classifier: Programming Language :: Python :: 3.8
Classifier: Programming Language :: Python :: 3.9
Classifier: Programming Language :: Python :: 3.10
Classifier: Programming Language :: Python :: 3.11
Classifier: Programming Language :: Python :: 3.12
Classifier: Topic :: Software Development :: Libraries :: Python Modules
Classifier: Topic :: Documentation
Requires-Python: >=3.8
License-File: LICENSE
Requires-Dist: fastmcp
Requires-Dist: requests
Requires-Dist: beautifulsoup4
Requires-Dist: markdown
Requires-Dist: fuzzywuzzy
Requires-Dist: python-levenshtein
Dynamic: license-file
